savepagenow/__init__.py
savepagenow/api.py
savepagenow/exceptions.py
savepagenow-1.3.1.dist-info/licenses/LICENSE
savepagenow-1.3.1.dist-info/METADATA
savepagenow-1.3.1.dist-info/WHEEL
savepagenow-1.3.1.dist-info/entry_points.txt
savepagenow-1.3.1.dist-info/top_level.txt
savepagenow-1.3.1.dist-info/RECORD
