Metadata-Version: 2.4
Name: savepagenow
Version: 1.3.1
Summary: A simple Python wrapper and command-line interface for archive.org’s "Save Page Now" capturing service
Home-page: https://www.github.com/palewire/savepagenow/
Author: Ben Welsh
Author-email: b@palewi.re
License: MIT
Project-URL: Documentation, http://palewi.re/docs/savepagenow
Project-URL: Source, https://github.com/palewire/savepagenow
Project-URL: Tracker, https://github.com/palewire/savepagenow/issues
Classifier: Development Status :: 5 - Production/Stable
Classifier: Operating System :: OS Independent
Classifier: Intended Audience :: Developers
Classifier: Programming Language :: Python
Classifier: Programming Language :: Python :: 3
Classifier: Programming Language :: Python :: 3.10
Classifier: Programming Language :: Python :: 3.11
Classifier: Programming Language :: Python :: 3.12
Classifier: Programming Language :: Python :: 3.13
Classifier: License :: OSI Approved :: MIT License
License-File: LICENSE
Requires-Dist: requests
Requires-Dist: click
Dynamic: author
Dynamic: author-email
Dynamic: classifier
Dynamic: description
Dynamic: description-content-type
Dynamic: home-page
Dynamic: license
Dynamic: license-file
Dynamic: project-url
Dynamic: requires-dist
Dynamic: summary
